.gitignore
LICENSE
MANIFEST.in
pyproject.toml
requirements.txt
setup.py
isotree/__init__.py
isotree/cpp_interface.pyx
isotree.egg-info/PKG-INFO
isotree.egg-info/SOURCES.txt
isotree.egg-info/dependency_links.txt
isotree.egg-info/top_level.txt
src/crit.hpp
src/digamma.hpp
src/dist.hpp
src/exp_depth_table.hpp
src/extended.hpp
src/fit_model.hpp
src/formatted_exporters.cpp
src/headers_joined.hpp
src/helpers_iforest.hpp
src/impute.hpp
src/indexer.cpp
src/instantiate_template_headers.hpp
src/isoforest.hpp
src/isotree.hpp
src/merge_models.cpp
src/mult.hpp
src/other_helpers.hpp
src/predict.hpp
src/python_helpers.hpp
src/ref_indexer.hpp
src/serialize.cpp
src/sql.cpp
src/subset_models.cpp
src/utils.hpp
src/xoshiro.hpp
src/ziggurat.hpp
src/robinmap/LICENSE
src/robinmap/include/tsl/robin_growth_policy.h
src/robinmap/include/tsl/robin_hash.h
src/robinmap/include/tsl/robin_map.h
src/robinmap/include/tsl/robin_set.h