Metadata-Version: 2.1
Name: isotree
Version: 0.6.1
Summary: Isolation-Based Outlier Detection, Distance, and NA imputation
Home-page: https://github.com/david-cortes/isotree
Author: David Cortes
Keywords: isolation-forest,anomaly,outlier
License-File: LICENSE
